pysimverse/__init__.py
pysimverse/simulators/__init__.py
pysimverse/simulators/drone/__init__.py
pysimverse/simulators/drone/drone.py
pysimverse/simulators/drone/drone_manager.py
pysimverse-0.13.dist-info/METADATA
pysimverse-0.13.dist-info/WHEEL
pysimverse-0.13.dist-info/top_level.txt
pysimverse-0.13.dist-info/RECORD
